ecoact_api_client/__init__.py
ecoact_api_client/db_model/__init__.py
ecoact_api_client/domain_model/__init__.py
ecoact_api_client-0.0.1.dist-info/METADATA
ecoact_api_client-0.0.1.dist-info/WHEEL
ecoact_api_client-0.0.1.dist-info/RECORD
